{
    "os": "Linux-5.15.0-73-generic-x86_64-with-debian-bookworm-sid",
    "python": "3.7.13",
    "heartbeatAt": "2023-07-26T16:00:53.819150",
    "startedAt": "2023-07-26T16:00:51.089649",
    "docker": null,
    "cuda": null,
    "args": null,
    "state": "running",
    "program": "MNIST.ipynb",
    "root": "/home/macula/SMATousi/VAE_outlier/outlier_VAE",
    "git": {
        "remote": "git@github.com:SMATousi/outlier_VAE.git",
        "commit": "8475f9c0de533ccfe0085bb2bdd8f9e5f8695df1"
    },
    "email": "mohamadali.tousi@gmail.com",
    "host": "pupil",
    "username": "SMATousi",
    "executable": "/home/macula/SMATousi/.conda/envs/mac-deep/bin/python",
    "cpu_count": 16,
    "cpu_count_logical": 24,
    "cpu_freq": {
        "current": 3103.299333333334,
        "min": 800.0,
        "max": 4716.666666666667
    },
    "cpu_freq_per_core": [
        {
            "current": 3200.0,
            "min": 800.0,
            "max": 5100.0
        },
        {
            "current": 3200.0,
            "min": 800.0,
            "max": 5100.0
        },
        {
            "current": 847.822,
            "min": 800.0,
            "max": 5100.0
        },
        {
            "current": 3200.0,
            "min": 800.0,
            "max": 5100.0
        },
        {
            "current": 3200.0,
            "min": 800.0,
            "max": 5100.0
        },
        {
            "current": 3200.0,
            "min": 800.0,
            "max": 5100.0
        },
        {
            "current": 3200.0,
            "min": 800.0,
            "max": 5100.0
        },
        {
            "current": 3200.0,
            "min": 800.0,
            "max": 5100.0
        },
        {
            "current": 3200.0,
            "min": 800.0,
            "max": 5100.0
        },
        {
            "current": 3200.0,
            "min": 800.0,
            "max": 5100.0
        },
        {
            "current": 3200.0,
            "min": 800.0,
            "max": 5100.0
        },
        {
            "current": 3200.0,
            "min": 800.0,
            "max": 5100.0
        },
        {
            "current": 3200.0,
            "min": 800.0,
            "max": 5200.0
        },
        {
            "current": 3200.0,
            "min": 800.0,
            "max": 5200.0
        },
        {
            "current": 3200.0,
            "min": 800.0,
            "max": 5200.0
        },
        {
            "current": 3200.0,
            "min": 800.0,
            "max": 5200.0
        },
        {
            "current": 3200.0,
            "min": 800.0,
            "max": 3900.0
        },
        {
            "current": 3200.0,
            "min": 800.0,
            "max": 3900.0
        },
        {
            "current": 3200.0,
            "min": 800.0,
            "max": 3900.0
        },
        {
            "current": 3200.0,
            "min": 800.0,
            "max": 3900.0
        },
        {
            "current": 3200.0,
            "min": 800.0,
            "max": 3900.0
        },
        {
            "current": 3200.0,
            "min": 800.0,
            "max": 3900.0
        },
        {
            "current": 3200.0,
            "min": 800.0,
            "max": 3900.0
        },
        {
            "current": 3200.0,
            "min": 800.0,
            "max": 3900.0
        }
    ],
    "disk": {
        "total": 878.0525245666504,
        "used": 102.01693725585938
    },
    "gpu": "NVIDIA GeForce RTX 3090",
    "gpu_count": 1,
    "gpu_devices": [
        {
            "name": "NVIDIA GeForce RTX 3090",
            "memory_total": 25769803776
        }
    ],
    "memory": {
        "total": 31.04662322998047
    }
}
